goto.py
goto_label-0.1.2.dist-info/METADATA
goto_label-0.1.2.dist-info/WHEEL
goto_label-0.1.2.dist-info/top_level.txt
goto_label-0.1.2.dist-info/RECORD
