Metadata-Version: 2.1
Name: goto-label
Version: 0.1.2
Summary: A function decorator, that rewrites the bytecode, to enable goto in Python
Home-page: https://github.com/alimsk/goto-python
Author: Ali M
License: UNKNOWN
Platform: UNKNOWN
Requires-Python: >=3.9
